FloatDelDot.py
floatdeldot-1.1.6.dist-info/WHEEL
floatdeldot-1.1.6.dist-info/METADATA
floatdeldot-1.1.6.dist-info/RECORD
